newrelic_logger/__init__.py
newrelic_logger/handlers.py
newrelic_logger/newrelic_logger.py
new_relic_logger_for_python-0.2.0.dist-info/WHEEL
new_relic_logger_for_python-0.2.0.dist-info/METADATA
new_relic_logger_for_python-0.2.0.dist-info/RECORD
