Metadata-Version: 2.1
Name: new-relic-logger-for-python
Version: 0.2.0
Summary: Push logs into New Relic using standard python logger asynchronously.
License: MIT
Author: Andrés Peñaloza
Author-email: andres.penaloza@xintec.cl
Requires-Python: >=3.7,<4.0
Classifier: License :: OSI Approved :: MIT License
Classifier: Programming Language :: Python :: 3
Classifier: Programming Language :: Python :: 3.7
Classifier: Programming Language :: Python :: 3.8
Classifier: Programming Language :: Python :: 3.9
Requires-Dist: newrelic (>=6.2.0,<7.0.0)
Requires-Dist: requests (>=2.25.1,<3.0.0)
